{
   "data" : {
      "homepage" : {
         "was" : "http://www.sandcrawler.com/SWB"
      },
      "email" : {
         "changed_to" : "MartinThurn@iname.com",
         "was" : "mthurn@tasc.com"
      },
      "cpan_mail_alias" : {
         "was" : "publ"
      },
      "userid" : {
         "was" : "MTHURN"
      },
      "entered_by" : {
         "name" : "Martin Thurn",
         "id" : "MTHURN"
      },
      "asciiname" : {
         "was" : ""
      },
      "fullname" : {
         "was" : "Martin Thurn"
      }
   },
   "meta" : {
      "message_id" : "200203291840.TAA20730@pause.perl.org",
      "epoch" : 1017427218,
      "from" : "upload@p11.speed-link.de",
      "subject" : "User update for MTHURN",
      "file" : "10905.txt",
      "type" : "user_update"
   }
}
