{
   "data" : {
      "homepage" : "http://www.ninjacode.com/~deus_x",
      "email" : "deus_x@ninjacode.com",
      "userid" : "DEUSX",
      "enteredby" : "Kurt D. Starsinic",
      "Name" : "Leslie Michael Orchard"
   },
   "meta" : {
      "message_id" : "200002292139.WAA11610@p11.speed-link.de",
      "epoch" : 951860366,
      "from" : "upload@p11.speed-link.de",
      "subject" : "Welcome new user Leslie Michael Orchard",
      "file" : "1216.txt",
      "type" : "welcome_new_user"
   }
}
