{
   "data" : {
      "userid" : {
         "name" : "Raul Dias",
         "id" : "RSD"
      },
      "description" : "Generic API to any User Interface",
      "communities" : "#perl #gtk+",
      "chapterid" : {
         "name" : "User_Interfaces",
         "id" : "8"
      },
      "similar" : "",
      "DSLIP" : "cdpOg",
      "modid" : "UI",
      "enteredon" : "Mon Aug 26 02:11:31 2002 GMT",
      "enteredby" : {
         "name" : "Raul Dias",
         "id" : "RSD"
      },
      "PS" : "The following links are only valid for module list maintainers:",
      "rationale" : "The idea behind UI.pm is that a application may use its OO API to\n    create a User Interface.\n\n    The user Interface can be anything that a Backend has being written\n    for, like: Gtk+ Qt Curses NCurses Web\n\n    So the application can run using whatever resource (GUI) is\n    available."
   },
   "meta" : {
      "message_id" : "200208260211.g7Q2BWV26789@pause.perl.org",
      "epoch" : 1030327892,
      "from" : "upload@p11.speed-link.de",
      "subject" : "Module submission UI",
      "file" : "13415.txt",
      "type" : "module_submission"
   }
}
