{
   "data" : {
      "chapterid" : "4 (Operating_System_Interfaces)",
      "modid" : "Schedule::Load",
      "userid" : {
         "name" : null,
         "id" : null
      },
      "enteredon" : "Wed Apr  5 20:00:58 2000 GMT",
      "enteredby" : "ANDK (Andreas J. König)",
      "description" : "Remote system load, processes, scheduling",
      "DSLI" : "RdpO"
   },
   "meta" : {
      "message_id" : "200004052000.WAA17596@p11.speed-link.de",
      "epoch" : 954964858,
      "from" : "upload@p11.speed-link.de",
      "subject" : "New module Schedule::Load",
      "file" : "1549.txt",
      "type" : "new_module"
   }
}
