{
   "data" : {
      "chapterid" : {
         "changed_to" : "12",
         "was" : "17"
      },
      "statd" : {
         "changed_to" : "c",
         "was" : "a"
      },
      "modid" : {
         "was" : "App::Manager"
      },
      "userid" : {
         "was" : "MLEHMANN"
      },
      "stats" : {
         "was" : "d"
      },
      "statl" : {
         "was" : "c"
      },
      "description" : {
         "was" : "Installing/Managing/Uninstalling Software"
      },
      "stati" : {
         "was" : "h"
      }
   },
   "meta" : {
      "message_id" : "200004102259.AAA22876@p11.speed-link.de",
      "epoch" : 955407576,
      "from" : "upload@p11.speed-link.de",
      "subject" : "Module update for App::Manager",
      "file" : "1606.txt",
      "type" : "module_update"
   }
}
