{
   "data" : {
      "chapterid" : "7 (Database_Interfaces)",
      "DSLIP" : "MdpOo",
      "modid" : "DBIx::HTML::PopupRadio",
      "userid" : {
         "name" : null,
         "id" : null
      },
      "enteredon" : "Wed Jan 15 08:38:22 2003 GMT",
      "enteredby" : "JV (Johan Vromans)",
      "description" : "Convert db data to popup menu or radio group"
   },
   "meta" : {
      "message_id" : "200301150838.h0F8cMo26617@pause.perl.org",
      "epoch" : 1042619902,
      "from" : "upload@pause.x.perl.org",
      "subject" : "New module DBIx::HTML::PopupRadio",
      "file" : "16997.txt",
      "type" : "new_module"
   }
}
