{
   "data" : {
      "homepage" : "www.code-wizards.com",
      "userid" : "WHOM",
      "fullname" : "Wolfgang Hommel",
      "why" : "Advanced 'pure perl' Tk widgets.\n\n    Starting with Tk::MatchEntry, an entry widget with user-friendly\n    auto-completion modelled after the \"recipient\" entry fields in\n    modern email clients, with significant differences to existing\n    widgets (like HistEntry (cpan), JBrowseEntry (cpan) and\n    SelectionEntry (comp.lang.perl.tk)). POD online at\n    http://www.code-wizards.com/projects/tk-matchentry/Tk-MatchEntry.3.html\n    .",
      "mail" : "CENSORED"
   },
   "meta" : {
      "message_id" : "200301301738.h0UHcv419099@pause.perl.org",
      "epoch" : 1043948337,
      "from" : "upload@pause.x.perl.org",
      "subject" : "PAUSE ID request (WHOM; Wolfgang Hommel)",
      "file" : "17501.txt",
      "type" : "pause_id_request"
   }
}
