{
   "data" : {
      "homepage" : "http://joseweeks.com",
      "userid" : "JOSEWEEKS",
      "fullname" : "Jose Marti Weeks",
      "why" : "I've written a set of modules that can be used to access the\n    everything2.com collaborative database (project homepage:\n    http://joseweeks.com/e2interface/). I'd like to make these\n    accessible via CPAN.",
      "mail" : "CENSORED"
   },
   "meta" : {
      "message_id" : "200303071523.h27FN1e24536@pause.perl.org",
      "epoch" : 1047050581,
      "from" : "upload@pause.x.perl.org",
      "subject" : "PAUSE ID request (JOSEWEEKS; Jose Marti Weeks)",
      "file" : "19299.txt",
      "type" : "pause_id_request"
   }
}
