{
   "data" : {
      "homepage" : {
         "changed_to" : "",
         "was" : "http://www.Michael-Forman.com"
      },
      "email" : {
         "was" : "Michael.Forman@Colorado.EDU"
      },
      "cpan_mail_alias" : {
         "was" : "publ"
      },
      "userid" : {
         "was" : "FORMAN"
      },
      "entered_by" : {
         "name" : "Michael Forman (マイケル　フォマン）",
         "id" : "FORMAN"
      },
      "asciiname" : {
         "was" : "Michael Forman"
      },
      "fullname" : {
         "changed_to" : "Michael Forman (マイケル　フォマン）",
         "was" : "Michael Forman マイケル フォマン"
      }
   },
   "meta" : {
      "message_id" : "200303090436.h294a8Z16439@pause.perl.org",
      "epoch" : 1047184568,
      "from" : "upload@pause.x.perl.org",
      "subject" : "User update for FORMAN",
      "file" : "19325.txt",
      "type" : "user_update"
   }
}
