{
   "data" : {
      "userid" : {
         "name" : "Bruno Tavares",
         "id" : "BMAVT"
      },
      "description" : "Module to manage a album (collection) of mp3",
      "communities" : "",
      "chapterid" : {
         "name" : "Miscellaneous_Modules",
         "id" : "23"
      },
      "similar" : "",
      "DSLIP" : "idpOp",
      "modid" : "MP3::Album",
      "enteredon" : "Mon Mar 10 16:58:55 2003 GMT",
      "enteredby" : {
         "name" : "Bruno Tavares",
         "id" : "BMAVT"
      },
      "PS" : "The following links are only valid for module list maintainers:",
      "rationale" : "This module will manage a collection of mp3 files. It will\n    \"simulate\" a music cd with the mp3 files and try to match with a\n    cddb database (freedb by default). It will permit to create tags for\n    the files in the album and to rename the files according a cddb\n    match."
   },
   "meta" : {
      "message_id" : "200303101658.h2AGwug04689@pause.perl.org",
      "epoch" : 1047315536,
      "from" : "upload@pause.x.perl.org",
      "subject" : "Module submission MP3::Album",
      "file" : "19358.txt",
      "type" : "module_submission"
   }
}
