{
   "data" : {
      "userid" : {
         "name" : "Casey West",
         "id" : "CWEST"
      },
      "description" : "POE Based SMTP Server with Plugin Support",
      "communities" : "http://opensource.dyndns.org",
      "chapterid" : {
         "name" : "Server_and_Daemon_Utilities",
         "id" : "16"
      },
      "similar" : "",
      "DSLIP" : "cdpOp",
      "modid" : "POEST::Server",
      "enteredon" : "Thu Mar 20 17:05:25 2003 GMT",
      "enteredby" : {
         "name" : "Casey West",
         "id" : "CWEST"
      },
      "PS" : "The following links are only valid for module list maintainers:",
      "rationale" : "POEST::Server is the highest-level class library that supports this\n    application, called poest. The application was named poest because\n    it is based on POE, and as a mail server acts as a traditional\n    \"post\". That is, the \"post\" delivers mail, \"poest\" delivers email.\n    As supporting libraries, POEST was the most logical choice.\n    Alphabetically, it aligns well with POE, though does not fit under\n    that namespace."
   },
   "meta" : {
      "message_id" : "200303201705.h2KH5Pd13171@pause.perl.org",
      "epoch" : 1048179925,
      "from" : "upload@pause.x.perl.org",
      "subject" : "Module submission POEST::Server",
      "file" : "19623.txt",
      "type" : "module_submission"
   }
}
