{
   "data" : {
      "userid" : {
         "name" : "☺唐宗漢☻",
         "id" : "AUTRIJUS"
      },
      "description" : "Use other catalog formats in Maketext",
      "communities" : "perl-i18n@perl.org,\n    p4://p4.elixus.org/member/autrijus/Locale-Maketext-Lexicon",
      "chapterid" : {
         "name" : "Internationalization_Locale",
         "id" : "13"
      },
      "similar" : "Locale::Maketext",
      "DSLIP" : "Rdppp",
      "modid" : "Locale::Maketext::Lexicon",
      "enteredon" : "Sun Mar 23 18:48:04 2003 GMT",
      "enteredby" : {
         "name" : "☺唐宗漢☻",
         "id" : "AUTRIJUS"
      },
      "PS" : "The following links are only valid for module list maintainers:",
      "rationale" : "This module provides lexicon-handling modules to read from other\n    local- ization formats, such as Gettext, Msgcat, and so on. It helps\n    adoption of the Locale::Maketext framework by allowing users to\n    manage lexicon files in the ubiquitous Gettext .po format, or store\n    them in a tied database. CPANPLUS, RT and various other projects has\n    been using this module for their I18N needs with success.\n\n    See http://aut.dyndns.org/webl10n/ for an introduction to this\n    module and its methodology."
   },
   "meta" : {
      "message_id" : "200303231848.h2NIm4s28579@pause.perl.org",
      "epoch" : 1048445284,
      "from" : "upload@pause.x.perl.org",
      "subject" : "Module submission Locale::Maketext::Lexicon",
      "file" : "19701.txt",
      "type" : "module_submission"
   }
}
