{
   "data" : {
      "homepage" : "http://www.thiesenweb.de",
      "userid" : "MARCUS",
      "fullname" : "Marcus Thiesen",
      "why" : "Taking over Curses::UI (allowed by Maurice Maakay) Delivering\n    CPANPLUS::Shell::Curses based on that",
      "mail" : "CENSORED"
   },
   "meta" : {
      "message_id" : "200303251359.h2PDxb023300@pause.perl.org",
      "epoch" : 1048600777,
      "from" : "upload@pause.x.perl.org",
      "subject" : "PAUSE ID request (MARCUS; Marcus Thiesen)",
      "file" : "19811.txt",
      "type" : "pause_id_request"
   }
}
