{
   "data" : {
      "userid" : {
         "was" : "KVAIL"
      },
      "stats" : {
         "was" : "d"
      },
      "description" : {
         "was" : "A hash with strict-like semantics"
      },
      "stati" : {
         "was" : "O"
      },
      "chapterid" : {
         "was" : " 6"
      },
      "modid" : {
         "was" : "Tie::StrictHash"
      },
      "statd" : {
         "was" : "R"
      },
      "mlstatus" : {
         "was" : "list"
      },
      "statl" : {
         "was" : "p"
      },
      "statp" : {
         "changed_to" : "?",
         "was" : "p"
      }
   },
   "meta" : {
      "message_id" : "200303261921.h2QJLSt08453@pause.perl.org",
      "epoch" : 1048706488,
      "from" : "upload@pause.x.perl.org",
      "subject" : "Module update for Tie::StrictHash",
      "file" : "19874.txt",
      "type" : "module_update"
   }
}
