{
   "data" : {
      "cpan_mail_alias" : {
         "changed_to" : "publ",
         "was" : "secr"
      },
      "userid" : {
         "was" : "AHORNBY"
      },
      "asciiname" : {
         "was" : ""
      },
      "ustatus" : {
         "was" : "unused"
      },
      "email" : {
         "was" : "CENSORED"
      },
      "homepage" : {
         "was" : "http://www.hornby.org.uk/"
      },
      "fullname" : {
         "was" : "Alex Hornby"
      },
      "entered_by" : {
         "name" : "Alex Hornby",
         "id" : "AHORNBY"
      }
   },
   "meta" : {
      "message_id" : "200305212037.h4LKboeP015903@pause.perl.org",
      "epoch" : 1053549470,
      "from" : "upload@pause.x.perl.org",
      "subject" : "User update for AHORNBY",
      "file" : "21265.txt",
      "type" : "user_update"
   }
}
