{
   "data" : {
      "cpan_mail_alias" : {
         "was" : "publ"
      },
      "userid" : {
         "was" : "JAMESP"
      },
      "asciiname" : {
         "was" : ""
      },
      "ustatus" : {
         "was" : "unused"
      },
      "email" : {
         "was" : "CENSORED"
      },
      "homepage" : {
         "changed_to" : "",
         "was" : "http://www.pcxperience.org/"
      },
      "fullname" : {
         "was" : "James A. Pattie"
      },
      "entered_by" : {
         "name" : "James A. Pattie",
         "id" : "JAMESP"
      }
   },
   "meta" : {
      "message_id" : "200306042123.h54LNelB026047@pause.perl.org",
      "epoch" : 1054761820,
      "from" : "upload@pause.x.perl.org",
      "subject" : "User update for JAMESP",
      "file" : "21514.txt",
      "type" : "user_update"
   }
}
