{
   "data" : {
      "userid" : {
         "name" : "M Carter Brown",
         "id" : "CARTER"
      },
      "description" : "Creates quick WML content",
      "communities" : "Wireless Chat, and Messageboard:\n    http://www.mcarterbrown.com/index.wml",
      "chapterid" : {
         "name" : "World_Wide_Web_HTML_HTTP_CGI",
         "id" : "15"
      },
      "similar" : "WML::Card WML::Deck",
      "DSLIP" : "adpfg",
      "modid" : "WML::Easy",
      "enteredon" : "Sat Jul 26 19:37:42 2003 GMT",
      "enteredby" : {
         "name" : "M Carter Brown",
         "id" : "CARTER"
      },
      "PS" : "The following links are only valid for module list maintainers:",
      "rationale" : "The module I'm currently working on will allow users to create a\n    new WML page, with one line of code. They can then print out\n    information from their HTML database, or something new, use the\n    module easily convert HTML code to the appropirate WML script, and\n    then end the page.\n\n    Allowing anyone to easily run a WML information site or even a\n    dynamic site as the one that was built here:\n    http://www.mcarterbrown.com/index.wml where I have a Wireless Mesage\n    Board, and a Wireless Multiple Chat rooms, built on the basis of\n    this module.\n\n    The other modules that I listed above are also good. But also very\n    complex. So complex so, that you really need to know WML well.\n\n    I'm writing it so that even the most novice module user can easily\n    create a WML page, hence the WML::Easy"
   },
   "meta" : {
      "message_id" : "200307261937.h6QJbgOd013968@pause.perl.org",
      "epoch" : 1059248262,
      "from" : "upload@pause.perl.org",
      "subject" : "Module submission WML::Easy",
      "file" : "22556.txt",
      "type" : "module_submission"
   }
}
