{
   "data" : {
      "chapterid" : "7 (Database_Interfaces)",
      "DSLIP" : "RdpOp",
      "modid" : "CDDB::Fake",
      "userid" : {
         "name" : null,
         "id" : null
      },
      "enteredon" : "Sat Jul 26 16:02:27 2003 GMT",
      "enteredby" : "JV (Johan Vromans)",
      "description" : "Fallback for missing CDDB info files"
   },
   "meta" : {
      "message_id" : "200307261602.h6QG2R2E011764@pause.perl.org",
      "epoch" : 1059235347,
      "from" : "upload@pause.perl.org",
      "subject" : "New module CDDB::Fake",
      "file" : "22552.txt",
      "type" : "new_module"
   }
}
