{
   "data" : {
      "chapterid" : "8 (User_Interfaces)",
      "DSLIP" : "RdpOb",
      "modid" : "Term::Activity",
      "userid" : {
         "name" : null,
         "id" : null
      },
      "enteredon" : "Tue Sep 23 20:30:05 2003 GMT",
      "enteredby" : "AUTRIJUS (☺唐宗漢☻)",
      "description" : "Term display of processing activity"
   },
   "meta" : {
      "message_id" : "200309232030.h8NKU5pu025082@pause.perl.org",
      "epoch" : 1064349005,
      "from" : "upload@pause.perl.org",
      "subject" : "New module Term::Activity",
      "file" : "23687.txt",
      "type" : "new_module"
   }
}
