{
   "data" : {
      "homepage" : "",
      "userid" : "DANSCH",
      "fullname" : "Daniel Schmeck",
      "why" : "I'm planning to contribute a moudule named Ebay::Lister. I have my\n    own little project for a programm similar to TurboLister from Ebay.\n    This programm is written in perl. ;-)\n\n    It should be work on every operating system, where perl worked , as\n    a console programm. For systems with qt I will contribute a\n    qt-frontend.",
      "mail" : "CENSORED"
   },
   "meta" : {
      "message_id" : "200401251307.i0PD7mjM031957@pause.perl.org",
      "epoch" : 1075036068,
      "from" : "upload@pause.perl.org",
      "subject" : "PAUSE ID request (DANSCH; Daniel Schmeck)",
      "file" : "25901.txt",
      "type" : "pause_id_request"
   }
}
