{
   "data" : {
      "chapterid" : {
         "was" : "19"
      },
      "statd" : {
         "was" : "a"
      },
      "modid" : {
         "was" : "Mail::Alias"
      },
      "userid" : {
         "changed_to" : "GBARR",
         "was" : "ZELT"
      },
      "stats" : {
         "was" : "d"
      },
      "statl" : {
         "was" : "p"
      },
      "description" : {
         "was" : "Reading/Writing/expanding of mail aliases"
      },
      "stati" : {
         "was" : "O"
      }
   },
   "meta" : {
      "message_id" : "200008291019.MAA08644@p11.speed-link.de",
      "epoch" : 967544382,
      "from" : "upload@p11.speed-link.de",
      "subject" : "Module update for Mail::Alias",
      "file" : "2753.txt",
      "type" : "module_update"
   }
}
