{
   "data" : {
      "userid" : {
         "name" : "Steffen Goeldner",
         "id" : "SGOELDNER"
      },
      "description" : "Load, create, manipulate, save pbm files",
      "communities" : "module-authors@perl.org",
      "chapterid" : {
         "name" : "Images_Pixmaps_Bitmaps",
         "id" : "18"
      },
      "similar" : "Image::Base Image::Xbm Image::PBMlib",
      "DSLIP" : "bdpOp",
      "modid" : "Image::Pbm",
      "enteredon" : "Mon Mar 29 09:53:46 2004 GMT",
      "enteredby" : {
         "name" : "Steffen Goeldner",
         "id" : "SGOELDNER"
      },
      "PS" : "The following links are only valid for module list maintainers:",
      "rationale" : "This module implements pbm (portable bitmap) specific load() and\n    save() methods for the Image::Base interface (using Image::Xbm and\n    Image::PBMlib). Thus it's similar to Image::Xpm and Image::Xbm."
   },
   "meta" : {
      "message_id" : "200403290953.i2T9rn7j014158@pause.perl.org",
      "epoch" : 1080554029,
      "from" : "upload@pause.perl.org",
      "subject" : "Module submission Image::Pbm",
      "file" : "30184.txt",
      "type" : "module_submission"
   }
}
