{
   "data" : {
      "homepage" : "",
      "userid" : "CANPANIEL",
      "fullname" : "Pablo Daniel Cano",
      "why" : "A MVC framework for web development supporting cgi and mod_perl\n    environments. In some way, similar tu struts (java). It has been\n    used for internal development, now I am preparing a public release.",
      "mail" : "CENSORED"
   },
   "meta" : {
      "message_id" : "200404212212.i3LMCMt8015220@pause.perl.org",
      "epoch" : 1082585542,
      "from" : "upload@pause.perl.org",
      "subject" : "PAUSE ID request (CANPANIEL; Pablo Daniel Cano)",
      "file" : "31048.txt",
      "type" : "pause_id_request"
   }
}
