{
   "data" : {
      "homepage" : "",
      "userid" : "VIDUR",
      "fullname" : "Vidur Apparao",
      "why" : "PerlUPnP (http://perlupnp.sourceforge.net) - A pure Perl Universal\n    Plug and Play implementation, supporting both Device and\n    ControlPoint developers.",
      "mail" : "CENSORED"
   },
   "meta" : {
      "message_id" : "200404301805.i3UI5jaG031145@pause.perl.org",
      "epoch" : 1083348345,
      "from" : "upload@pause.perl.org",
      "subject" : "PAUSE ID request (VIDUR; Vidur Apparao)",
      "file" : "31362.txt",
      "type" : "pause_id_request"
   }
}
