{
   "data" : {
      "cpan_mail_alias" : {
         "changed_to" : "none",
         "was" : "publ"
      },
      "userid" : {
         "was" : "MHOYT"
      },
      "asciiname" : {
         "was" : ""
      },
      "ustatus" : {
         "was" : "unused"
      },
      "email" : {
         "was" : "CENSORED"
      },
      "homepage" : {
         "was" : ""
      },
      "fullname" : {
         "was" : "Michael Hoyt"
      },
      "entered_by" : {
         "name" : "Michael Hoyt",
         "id" : "MHOYT"
      }
   },
   "meta" : {
      "message_id" : "200405161550.i4GFoMSf032279@pause.perl.org",
      "epoch" : 1084722622,
      "from" : "upload@pause.perl.org",
      "subject" : "User update for MHOYT",
      "file" : "31948.txt",
      "type" : "user_update"
   }
}
