{
   "data" : {
      "homepage" : "",
      "userid" : "BALESHI",
      "fullname" : "John Baleshiski",
      "why" : "Various Perl modules that include network manipulation of data, all\n    released under the KT namespace.",
      "mail" : "CENSORED"
   },
   "meta" : {
      "message_id" : "200405231523.i4NFNND0011549@pause.perl.org",
      "epoch" : 1085325803,
      "from" : "upload@pause.perl.org",
      "subject" : "PAUSE ID request (BALESHI; John Baleshiski)",
      "file" : "32188.txt",
      "type" : "pause_id_request"
   }
}
