{
   "data" : {
      "homepage" : {
         "was" : ""
      },
      "email" : {
         "was" : "CENSORED"
      },
      "cpan_mail_alias" : {
         "was" : "publ"
      },
      "userid" : {
         "was" : "RVASICEK"
      },
      "entered_by" : {
         "name" : "Roman Vasicek",
         "id" : "RVASICEK"
      },
      "asciiname" : {
         "changed_to" : "",
         "was" : "Roman Vasicek"
      },
      "fullname" : {
         "changed_to" : "Roman Vasicek",
         "was" : "Roman Vašíček"
      }
   },
   "meta" : {
      "message_id" : "200406090726.i597QnQT030375@pause.perl.org",
      "epoch" : 1086766009,
      "from" : "upload@pause.perl.org",
      "subject" : "User update for RVASICEK",
      "file" : "32731.txt",
      "type" : "user_update"
   }
}
