{
   "data" : {
      "userid" : {
         "name" : "Jason Michelizzi",
         "id" : "JASONM"
      },
      "description" : "measure the similarity of text documents",
      "communities" : "",
      "chapterid" : {
         "name" : "String_Lang_Text_Proc",
         "id" : "11"
      },
      "similar" : "",
      "DSLIP" : "adpOg",
      "modid" : "Text::Similarity",
      "enteredon" : "Mon Sep 13 16:07:26 2004 GMT",
      "enteredby" : {
         "name" : "Jason Michelizzi",
         "id" : "JASONM"
      },
      "PS" : "The following links are only valid for module list maintainers:",
      "rationale" : "This project will produce a set of machine measures of text\n    document similarity. A measure of document similarity quantifies the\n    degree to which two text documents are related. For example, two\n    news stories about the same event should result in a high similarty\n    score."
   },
   "meta" : {
      "message_id" : "200409131607.i8DG7QMd009609@pause.perl.org",
      "epoch" : 1095091646,
      "from" : "upload@pause.perl.org",
      "subject" : "Module submission Text::Similarity",
      "file" : "34724.txt",
      "type" : "module_submission"
   }
}
