{
   "data" : {
      "cpan_mail_alias" : {
         "changed_to" : "none",
         "was" : "publ"
      },
      "userid" : {
         "was" : "SPACEMAN"
      },
      "asciiname" : {
         "was" : ""
      },
      "ustatus" : {
         "was" : "unused"
      },
      "email" : {
         "was" : "CENSORED"
      },
      "homepage" : {
         "was" : "http://myhome.spu.edu/spaceman"
      },
      "fullname" : {
         "was" : "Adam Blinkinsop"
      },
      "entered_by" : {
         "name" : "Adam Blinkinsop",
         "id" : "SPACEMAN"
      }
   },
   "meta" : {
      "message_id" : "200410291606.i9TG6tuq031649@pause.perl.org",
      "epoch" : 1099066015,
      "from" : "upload@pause.perl.org",
      "subject" : "User update for SPACEMAN",
      "file" : "36007.txt",
      "type" : "user_update"
   }
}
