{
   "data" : {
      "homepage" : {
         "was" : ""
      },
      "email" : {
         "was" : "CENSORED"
      },
      "cpan_mail_alias" : {
         "was" : "secr"
      },
      "userid" : {
         "was" : "ROLAND"
      },
      "entered_by" : {
         "name" : "Roland Huß",
         "id" : "ROLAND"
      },
      "asciiname" : {
         "was" : "Roland Huss"
      },
      "fullname" : {
         "was" : "Roland Huß"
      }
   },
   "meta" : {
      "message_id" : "200501031828.j03IS9in030661@pause.perl.org",
      "epoch" : 1104776889,
      "from" : "upload@pause.perl.org",
      "subject" : "User update for ROLAND",
      "file" : "37400.txt",
      "type" : "user_update"
   }
}
