{
   "data" : {
      "userid" : {
         "name" : "Damien Krotkine",
         "id" : "DAMS"
      },
      "description" : "layer on top of perl gtk2",
      "communities" : "",
      "chapterid" : {
         "name" : "User_Interfaces",
         "id" : "8"
      },
      "similar" : "",
      "DSLIP" : "bdphg",
      "modid" : "Gtk2Fu",
      "enteredon" : "Fri Jan  7 00:51:55 2005 GMT",
      "enteredby" : {
         "name" : "Damien Krotkine",
         "id" : "DAMS"
      },
      "PS" : "The following links are only valid for module list maintainers:",
      "rationale" : ""
   },
   "meta" : {
      "message_id" : "200501070051.j070pu7j016414@pause.perl.org",
      "epoch" : 1105059118,
      "from" : "upload@pause.perl.org",
      "subject" : "Module submission Gtk2Fu",
      "file" : "37497.txt",
      "type" : "module_submission"
   }
}
