{
   "data" : {
      "userid" : {
         "name" : "Sebastian Basilio",
         "id" : "SILI"
      },
      "description" : "Easy management for Text::Template objects",
      "communities" : "",
      "chapterid" : {
         "name" : "String_Lang_Text_Proc",
         "id" : "11"
      },
      "similar" : "",
      "DSLIP" : "SdpOp",
      "modid" : "Text::Template::Queue",
      "enteredon" : "Thu Feb  3 06:07:27 2005 GMT",
      "enteredby" : {
         "name" : "Sebastian Basilio",
         "id" : "SILI"
      },
      "PS" : "The following links are only valid for module list maintainers:",
      "rationale" : ""
   },
   "meta" : {
      "message_id" : "200502030607.j1367SW4028347@pause.perl.org",
      "epoch" : 1107410848,
      "from" : "upload@pause.perl.org",
      "subject" : "Module submission Text::Template::Queue",
      "file" : "38108.txt",
      "type" : "module_submission"
   }
}
