{
   "data" : {
      "homepage" : {
         "changed_to" : "http://www.kenwu.idv.tw/",
         "was" : "http://blog.yam.com/kenwu/"
      },
      "email" : {
         "was" : "CENSORED"
      },
      "cpan_mail_alias" : {
         "was" : "publ"
      },
      "userid" : {
         "was" : "KENWU"
      },
      "entered_by" : {
         "name" : "莉洛",
         "id" : "KENWU"
      },
      "asciiname" : {
         "was" : "Lilo Huang"
      },
      "fullname" : {
         "was" : "莉洛"
      }
   },
   "meta" : {
      "message_id" : "200607221707.k6MH7hnC008205@pause.perl.org",
      "epoch" : 1153588063,
      "from" : "upload@pause.perl.org",
      "subject" : "User update for KENWU",
      "file" : "49970.txt",
      "type" : "user_update"
   }
}
