{
   "data" : {
      "userid" : {
         "name" : "Strzelecki Łukasz",
         "id" : "STRZELEC"
      },
      "description" : "Speeds up ANY CGI script.",
      "communities" : "http://warszawa.pm.org",
      "chapterid" : {
         "name" : "World_Wide_Web_HTML_HTTP_CGI",
         "id" : "15"
      },
      "similar" : "",
      "DSLIP" : "Rdpnp",
      "modid" : "CGI::SpeedUp",
      "enteredon" : "Fri Apr 11 19:30:45 2008 GMT",
      "enteredby" : {
         "name" : "Strzelecki Łukasz",
         "id" : "STRZELEC"
      },
      "PS" : "The following links are only valid for module list maintainers:",
      "rationale" : "The CGI::SpeedUp module provides a simple way to speed up any CGI\n    application by managing its STDOUT and STDERR."
   },
   "meta" : {
      "message_id" : "200804111930.m3BJUjnF023038@pause.perl.org",
      "epoch" : 1207942245,
      "from" : "upload@pause.perl.org",
      "subject" : "Module submission CGI::SpeedUp",
      "file" : "59988.txt",
      "type" : "module_submission"
   }
}
