{
   "data" : {
      "homepage" : "http://kato.iki.fi/",
      "userid" : "KORPIQ",
      "fullname" : "Kalle Hallivuori",
      "why" : "Test::Mock − trivial planning of sub call flows for fast unit test\n    writing.\n\n    Easier to use and more comprehensive than Test::MockObject,\n    Test::MockModule or Test::MockClass. I'd have named it YAMock but\n    rather saved two letters :)",
      "mail" : "CENSORED"
   },
   "meta" : {
      "message_id" : "200901182103.n0IL30vO010947@pause.perl.org",
      "epoch" : 1232312580,
      "from" : "upload@pause.perl.org",
      "subject" : "PAUSE ID request (KORPIQ; Kalle Hallivuori)",
      "file" : "64117.txt",
      "type" : "pause_id_request"
   }
}
