{
   "data" : {
      "userid" : {
         "name" : "Андрій Костенко",
         "id" : "GUGU"
      },
      "description" : "Perl interface to libcroco",
      "communities" : "bugtrac + subversion for now",
      "chapterid" : {
         "name" : "String_Lang_Text_Proc",
         "id" : "11"
      },
      "similar" : "CSS, CSS::DOM",
      "DSLIP" : "bdcOp",
      "modid" : "CSS::Croco",
      "enteredon" : "Sun Nov 22 20:59:44 2009 GMT",
      "PS" : "The following links are only valid for module list maintainers:",
      "enteredby" : {
         "name" : "Андрій Костенко",
         "id" : "GUGU"
      },
      "rationale" : "This module is very fast, because it uses CSS library libcroco. It\n    uses namespace CSS (bfcause it is a CSS parser) and Croco as it uses\n    libcroco.\n\n    PS: anybody here?? there are no answer about previous my request"
   },
   "meta" : {
      "message_id" : "200911222059.nAMKxiv9019047@pause.fiz-chemie.de",
      "epoch" : 1258923584,
      "from" : "upload@pause.perl.org",
      "subject" : "Module submission CSS::Croco",
      "file" : "68638.txt",
      "type" : "module_submission"
   }
}
