{
   "data" : {
      "userid" : {
         "name" : "広木　大地",
         "id" : "HDAICHI"
      },
      "description" : "Global Cache per Request for Plack Server",
      "communities" : "",
      "chapterid" : {
         "name" : "World_Wide_Web_HTML_HTTP_CGI",
         "id" : "15"
      },
      "similar" : "",
      "DSLIP" : "cdpOp",
      "modid" : "Plack::Middleware::ScopeSession",
      "enteredon" : "Sat Dec 19 05:28:43 2009 GMT",
      "enteredby" : {
         "name" : "広木　大地",
         "id" : "HDAICHI"
      },
      "PS" : "The following links are only valid for module list maintainers:",
      "rationale" : ""
   },
   "meta" : {
      "message_id" : "200912190528.nBJ5ShDQ015821@pause.fiz-chemie.de",
      "epoch" : 1261200523,
      "from" : "upload@pause.perl.org",
      "subject" : "Module submission Plack::Middleware::ScopeSession",
      "file" : "69010.txt",
      "type" : "module_submission"
   }
}
