{
   "data" : {
      "userid" : {
         "name" : "陈钢",
         "id" : "CHENGANG"
      },
      "description" : "Extend <system> to Allow Timeout",
      "communities" : "modules@perl.org",
      "chapterid" : {
         "name" : "Language_Extensions",
         "id" : "2"
      },
      "similar" : "",
      "DSLIP" : "Rdpfp",
      "modid" : "System::Timeout",
      "enteredon" : "Wed Jun  8 15:25:10 2011 GMT",
      "enteredby" : {
         "name" : "陈钢",
         "id" : "CHENGANG"
      },
      "PS" : "The following links are only valid for module list maintainers:",
      "rationale" : "This module extends system() to allow timeout after the specified\n    seconds.\n\n    I think \"System::Timeout\" accurately describes what it is done.\n\n    So, people will get what them want when they search \"system\n    timeout\" on CPAN.I think that`s the keywords that people will type\n    in the search box."
   },
   "meta" : {
      "message_id" : "201106081525.p58FPAoh012659@pause.fiz-chemie.de",
      "epoch" : 1307546710,
      "from" : "upload@pause.perl.org",
      "subject" : "Module submission System::Timeout",
      "file" : "76393.txt",
      "type" : "module_submission"
   }
}
