{
   "data" : {
      "cpan_mail_alias" : {
         "was" : "secr"
      },
      "userid" : {
         "was" : "FUKUDA"
      },
      "asciiname" : {
         "was" : "Keisuke Fukuda"
      },
      "ustatus" : {
         "changed_to" : "unused",
         "was" : "delete"
      },
      "email" : {
         "was" : "CENSORED"
      },
      "homepage" : {
         "was" : "http://d.hatena.ne.jp/keisukefukuda"
      },
      "fullname" : {
         "was" : "福田圭祐"
      },
      "entered_by" : {
         "name" : "福田圭祐",
         "id" : "FUKUDA"
      }
   },
   "meta" : {
      "message_id" : "20130124121912.B740E1FF95@pause.perl.org",
      "epoch" : 1359029952,
      "from" : "upload@pause.perl.org",
      "subject" : "User update for FUKUDA",
      "file" : "84402.txt",
      "type" : "user_update"
   }
}
