{
   "data" : {
      "homepage" : "mooser.me",
      "userid" : "NIUMANG",
      "fullname" : " 舌尖上的牛氓 ",
      "why" : "A perl programer from china,worked in changsha,like to use perl do\n    some intresting things",
      "mail" : "CENSORED"
   },
   "meta" : {
      "message_id" : "20130421033332.BCBD51F898@pause.perl.org",
      "epoch" : 1366515212,
      "from" : "upload@pause.perl.org",
      "subject" : "PAUSE ID request (NIUMANG; =?UTF-8?Q?=20=EF=A3=BF=20=E8=88=8C=E5=B0=96=E4=B8=8A=E7=9A=84=E7=89=9B?= =?UTF-8?Q?=E6=B0=93=20=EF=A3=BF?=)",
      "file" : "85693.txt",
      "type" : "pause_id_request"
   }
}
